ktuvit/__init__.py
ktuvit/ktuvit.py
ktuvit_api-0.1.1.dist-info/LICENSE
ktuvit_api-0.1.1.dist-info/METADATA
ktuvit_api-0.1.1.dist-info/WHEEL
ktuvit_api-0.1.1.dist-info/top_level.txt
ktuvit_api-0.1.1.dist-info/RECORD
