Metadata-Version: 2.1
Name: ktuvit-api
Version: 0.1.1
Summary: Unofficial python client to ktuvit.me (screwzira) API 
Home-page: https://github.com/yious/ktuvit-api
License: UNKNOWN
Platform: UNKNOWN
Classifier: Programming Language :: Python :: 3
Classifier: Operating System :: OS Independent
Classifier: License :: OSI Approved :: GNU General Public License v3 (GPLv3)
Requires-Python: >=3.6
Requires-Dist: requests
